starkbank/__init__.py
starkbank/iso4217/__init__.py
starkbank/iso4217/currency.py
starkbank/iso8583/__init__.py
starkbank/iso8583/message.py
starkbank/iso8583/version.py
starkbank/iso8583/template/__init__.py
starkbank/iso8583/template/base.py
starkbank/iso8583/template/mastercard.py
starkbank/iso8583/template/visa.py
starkbank/iso8583/utils/__init__.py
starkbank/iso8583/utils/binary.py
starkbank/iso8583/utils/bitmap.py
starkbank/iso8583/utils/enum.py
starkbank/iso8583/utils/field.py
starkbank/iso8583/utils/header.py
starkbank/iso8583/utils/length.py
starkbank/iso8583/utils/pds.py
starkbank/iso8583/utils/parser/__init__.py
starkbank/iso8583/utils/parser/bcdString.py
starkbank/iso8583/utils/parser/binary.py
starkbank/iso8583/utils/parser/bitString.py
starkbank/iso8583/utils/parser/bitmap.py
starkbank/iso8583/utils/parser/bitmapFormat.py
starkbank/iso8583/utils/parser/dataset.py
starkbank/iso8583/utils/parser/de048.py
starkbank/iso8583/utils/parser/de112.py
starkbank/iso8583/utils/parser/hexadecimal.py
starkbank/iso8583/utils/parser/string.py
starkbank/iso8583/utils/parser/undefined.py
tests/__init__.py
tests/iso8583/__init__.py
tests/iso8583/testUtils.py
tests/iso8583/main/__init__.py
tests/iso8583/main/testIsoMessage.py
tests/iso8583/utils/__init__.py
tests/iso8583/utils/randomData.py
starkbank_iso8583-0.6.1.dist-info/LICENSE
starkbank_iso8583-0.6.1.dist-info/METADATA
starkbank_iso8583-0.6.1.dist-info/WHEEL
starkbank_iso8583-0.6.1.dist-info/top_level.txt
starkbank_iso8583-0.6.1.dist-info/RECORD
