Metadata-Version: 2.1
Name: starkbank-iso8583
Version: 0.6.1
Summary: Python library for conversion between ISO 8583 message standard and JSON
Home-page: https://github.com/starkbank/iso8583-python
Author: Stark Bank
Author-email: developers@starkbank.com
License: MIT License
Keywords: iso8583,credit card,debit card,mastercard,visa
Platform: UNKNOWN
License-File: LICENSE
